safecrypt/__init__.py
safecrypt/decrypt.py
safecrypt/encrypt.py
safecrypt/onezero.py
safe_dencrypt-0.2.dist-info/LICENSE
safe_dencrypt-0.2.dist-info/METADATA
safe_dencrypt-0.2.dist-info/WHEEL
safe_dencrypt-0.2.dist-info/top_level.txt
safe_dencrypt-0.2.dist-info/RECORD
