Metadata-Version: 2.1
Name: safe_dencrypt
Version: 0.2
Summary: A lib to decrypt or encrypt message convinet and safe!expert!
Home-page: https://kkgithub.com/ytsidle/safe-dencrypt
Author: Chenming Lai
Author-email: 18859950787@163.com
Classifier: Programming Language :: Python :: 3
Classifier: License :: OSI Approved :: MIT License
Classifier: Operating System :: OS Independent
License-File: LICENSE
